{"cameraMode":{"drawMode":0,"name":"Shaded","section":"Shading Mode"},"sceneLighting":true,"audioPlay":false,"sceneViewState":{"m_AlwaysRefresh":false,"showFog":true,"showSkybox":true,"showFlares":true,"showImageEffects":true,"showParticleSystems":true,"showVisualEffectGraphs":true,"m_FxEnabled":true},"in2DMode":false,"pivot":{"x":45.04909896850586,"y":4.145298004150391,"z":-5.507671356201172},"rotation":{"x":-0.0026584004517644645,"y":-0.8073314428329468,"z":0.003642705036327243,"w":-0.590116560459137},"size":22.137287139892579,"orthographic":false}